wiz_feishu/__init__.py
wiz_feishu/feishu_bot.py
wiz_feishu/generator.py
wiz_feishu-2.0.2.dist-info/METADATA
wiz_feishu-2.0.2.dist-info/WHEEL
wiz_feishu-2.0.2.dist-info/top_level.txt
wiz_feishu-2.0.2.dist-info/RECORD
